README.md
setup.py
modelhub/__init__.py
modelhub/settings.py
modelhub.egg-info/PKG-INFO
modelhub.egg-info/SOURCES.txt
modelhub.egg-info/dependency_links.txt
modelhub.egg-info/entry_points.txt
modelhub.egg-info/requires.txt
modelhub.egg-info/top_level.txt
modelhub/apis/__init__.py
modelhub/commands/__init__.py
modelhub/commands/base.py
modelhub/commands/checkout.py
modelhub/commands/config.py
modelhub/commands/copy.py
modelhub/commands/create.py
modelhub/commands/delete.py
modelhub/commands/export.py
modelhub/commands/info.py
modelhub/commands/inspect.py
modelhub/commands/inspect_checkpoint.py
modelhub/commands/list.py
modelhub/commands/path.py
modelhub/commands/push.py
modelhub/commands/putup.py
modelhub/commands/runserver.py
modelhub/commands/submit.py
modelhub/commands/version.py
modelhub/core/__init__.py
modelhub/core/apis.py
modelhub/core/conf.py
modelhub/core/exceptions.py
modelhub/core/models.py
modelhub/core/utils.py
modelhub/core/protos/__init__.py
modelhub/core/protos/model_pb2.py
modelhub/framework/__init__.py
modelhub/framework/base.py
modelhub/framework/parents.py
modelhub/framework/tf.py
modelhub/tf_serving/__init__.py
modelhub/tf_serving/auto_discovery.py
modelhub/utils/__init__.py
modelhub/utils/convert_freeze_graph.py
modelhub/utils/json.py
modelhub/utils/keras_export.py
modelhub/utils/numpy.py
modelhub/utils/watch_dog_model.py
tensorflow_protos/__init__.py
tensorflow_protos/core/__init__.py
tensorflow_protos/core/framework/__init__.py
tensorflow_protos/core/framework/allocation_description_pb2.py
tensorflow_protos/core/framework/attr_value_pb2.py
tensorflow_protos/core/framework/function_pb2.py
tensorflow_protos/core/framework/graph_pb2.py
tensorflow_protos/core/framework/node_def_pb2.py
tensorflow_protos/core/framework/op_def_pb2.py
tensorflow_protos/core/framework/resource_handle_pb2.py
tensorflow_protos/core/framework/summary_pb2.py
tensorflow_protos/core/framework/tensor_description_pb2.py
tensorflow_protos/core/framework/tensor_pb2.py
tensorflow_protos/core/framework/tensor_shape_pb2.py
tensorflow_protos/core/framework/tensor_slice_pb2.py
tensorflow_protos/core/framework/types_pb2.py
tensorflow_protos/core/framework/variable_pb2.py
