Metadata-Version: 1.0
Name: modelhub
Version: 3.0.6
Summary: Modelhub
Home-page: http://git.patsnap.com/research/modelhub
Author: Jay Young(yjmade)
Author-email: yangjian@patsnap.com
License: UNKNOWN
Platform: UNKNOWN
